arc1pyqt/__init__.py
arc1pyqt/__main__.py
arc1pyqt/constants.py
arc1pyqt/instrument.py
arc1pyqt/main.py
arc1pyqt/modutils.py
arc1pyqt/state.py
arc1pyqt/version.py
arc1pyqt/version.txt
arc1pyqt/ControlWidgets/__init__.py
arc1pyqt/ControlWidgets/about_widget.py
arc1pyqt/ControlWidgets/cell_widget.py
arc1pyqt/ControlWidgets/colorbar_widget.py
arc1pyqt/ControlWidgets/common.py
arc1pyqt/ControlWidgets/config_hardware_widget.py
arc1pyqt/ControlWidgets/crossbar_container_widget.py
arc1pyqt/ControlWidgets/crossbar_widget.py
arc1pyqt/ControlWidgets/data_display_widget.py
arc1pyqt/ControlWidgets/device_widget.py
arc1pyqt/ControlWidgets/flasher_dialog.py
arc1pyqt/ControlWidgets/history_tree_model.py
arc1pyqt/ControlWidgets/history_widget.py
arc1pyqt/ControlWidgets/logo_label_widget.py
arc1pyqt/ControlWidgets/manual_ops_widget.py
arc1pyqt/ControlWidgets/matrix_widget.py
arc1pyqt/ControlWidgets/module_path_widget.py
arc1pyqt/ControlWidgets/new_session_dialog.py
arc1pyqt/ControlWidgets/prog_panel_widget.py
arc1pyqt/ExtPanels/__init__.py
arc1pyqt/GeneratedUiElements/__init__.py
arc1pyqt/GeneratedUiElements/chronoamperometry.py
arc1pyqt/GeneratedUiElements/convergeToState.py
arc1pyqt/GeneratedUiElements/fitdialog.py
arc1pyqt/GeneratedUiElements/mss.py
arc1pyqt/GeneratedUiElements/pf.py
arc1pyqt/Globals/__init__.py
arc1pyqt/Globals/_antennae.py
arc1pyqt/Globals/fonts.py
arc1pyqt/Globals/functions.py
arc1pyqt/Globals/styles.py
arc1pyqt/Graphics/__init__.py
arc1pyqt/Graphics/about-banner.png
arc1pyqt/Graphics/appicon.png
arc1pyqt/Graphics/applogo.ico
arc1pyqt/Graphics/clear.png
arc1pyqt/Graphics/display-abs-cur.svg
arc1pyqt/Graphics/display-cond.svg
arc1pyqt/Graphics/display-cur.svg
arc1pyqt/Graphics/display-res.svg
arc1pyqt/Graphics/logo_white.svg
arc1pyqt/Graphics/new-session-banner.png
arc1pyqt/Graphics/new.png
arc1pyqt/Graphics/open.png
arc1pyqt/Graphics/platform-manager.png
arc1pyqt/Graphics/save.png
arc1pyqt/Graphics/splash.png
arc1pyqt/Helper/StandAlone32.txt
arc1_pyqt-2.0.0rc3.dist-info/LICENSE.txt
arc1_pyqt-2.0.0rc3.dist-info/METADATA
arc1_pyqt-2.0.0rc3.dist-info/WHEEL
arc1_pyqt-2.0.0rc3.dist-info/entry_points.txt
arc1_pyqt-2.0.0rc3.dist-info/top_level.txt
arc1_pyqt-2.0.0rc3.dist-info/RECORD
