Metadata-Version: 2.1
Name: arc1-pyqt
Version: 2.0.0rc3
Summary: ArC1 Control Interface
Home-page: http://www.arc-instruments.co.uk/products/arc-one/
Author: Spyros Stathopoulos
Author-email: devel@arc-instruments.co.uk
License: GPL3
Project-URL: Bug Tracker, https://github.com/arc-instruments/arc1_pyqt/issues
Project-URL: Source Code, https://github.com/arc-instruments/arc1_pyqt
Platform: any
Classifier: Development Status :: 4 - Beta
Classifier: Intended Audience :: Science/Research
Classifier: Topic :: Scientific/Engineering
Classifier: License :: OSI Approved :: GNU General Public License v3 or later (GPLv3+)
Classifier: Operating System :: Microsoft :: Windows
Classifier: Operating System :: POSIX
Classifier: Operating System :: MacOS :: MacOS X
Classifier: Programming Language :: Python :: 3 :: Only
Classifier: Programming Language :: Python :: 3.7
Classifier: Programming Language :: Python :: 3.8
Classifier: Programming Language :: Python :: 3.9
Requires-Python: >=3.6
License-File: LICENSE.txt
Requires-Dist: numpy (>=1.18.0)
Requires-Dist: PyQt5 (>=5.12.0)
Requires-Dist: pyqtgraph (>=0.12.3)
Requires-Dist: pyserial (>=3.0)
Requires-Dist: requests (>=2.20.0)
Requires-Dist: scipy (>=1.3.0)
Requires-Dist: semver (>=2.7.0)
Requires-Dist: importlib-resources (>=1.1.0) ; python_version < "3.7"
Requires-Dist: dataclasses (>=0.7) ; python_version < "3.7"
Requires-Dist: pywin32 (>=222) ; sys_platform == "win32"
